hatchet_sdk/__init__.py
hatchet_sdk/client.py
hatchet_sdk/clients/admin.py
hatchet_sdk/clients/dispatcher/action_listener.py
hatchet_sdk/clients/dispatcher/dispatcher.py
hatchet_sdk/clients/event_ts.py
hatchet_sdk/clients/events.py
hatchet_sdk/clients/listeners/durable_event_listener.py
hatchet_sdk/clients/listeners/pooled_listener.py
hatchet_sdk/clients/listeners/run_event_listener.py
hatchet_sdk/clients/listeners/workflow_listener.py
hatchet_sdk/clients/rest/__init__.py
hatchet_sdk/clients/rest/api/__init__.py
hatchet_sdk/clients/rest/api/api_token_api.py
hatchet_sdk/clients/rest/api/cel_api.py
hatchet_sdk/clients/rest/api/default_api.py
hatchet_sdk/clients/rest/api/event_api.py
hatchet_sdk/clients/rest/api/filter_api.py
hatchet_sdk/clients/rest/api/github_api.py
hatchet_sdk/clients/rest/api/healthcheck_api.py
hatchet_sdk/clients/rest/api/log_api.py
hatchet_sdk/clients/rest/api/metadata_api.py
hatchet_sdk/clients/rest/api/rate_limits_api.py
hatchet_sdk/clients/rest/api/slack_api.py
hatchet_sdk/clients/rest/api/sns_api.py
hatchet_sdk/clients/rest/api/step_run_api.py
hatchet_sdk/clients/rest/api/task_api.py
hatchet_sdk/clients/rest/api/tenant_api.py
hatchet_sdk/clients/rest/api/user_api.py
hatchet_sdk/clients/rest/api/webhook_api.py
hatchet_sdk/clients/rest/api/worker_api.py
hatchet_sdk/clients/rest/api/workflow_api.py
hatchet_sdk/clients/rest/api/workflow_run_api.py
hatchet_sdk/clients/rest/api/workflow_runs_api.py
hatchet_sdk/clients/rest/api_client.py
hatchet_sdk/clients/rest/api_response.py
hatchet_sdk/clients/rest/configuration.py
hatchet_sdk/clients/rest/exceptions.py
hatchet_sdk/clients/rest/models/__init__.py
hatchet_sdk/clients/rest/models/accept_invite_request.py
hatchet_sdk/clients/rest/models/api_error.py
hatchet_sdk/clients/rest/models/api_errors.py
hatchet_sdk/clients/rest/models/api_meta.py
hatchet_sdk/clients/rest/models/api_meta_auth.py
hatchet_sdk/clients/rest/models/api_meta_integration.py
hatchet_sdk/clients/rest/models/api_meta_posthog.py
hatchet_sdk-1.22.14.dist-info/METADATA
hatchet_sdk-1.22.14.dist-info/WHEEL
hatchet_sdk-1.22.14.dist-info/entry_points.txt
hatchet_sdk-1.22.14.dist-info/RECORD
